[
    {
        "type": 1,
        "name": "KAIST문지캠퍼스본원뒷편",
        "loc": [
            127.39973,
            36.39383
        ]
    },
    {
        "type": 1,
        "name": "한국과학기술원오리연못",
        "loc": [
            127.36252,
            36.36737
        ]
    },
    {
        "type": 1,
        "name": "한국과학기술원본관",
        "loc": [
            127.36071,
            36.3699
        ]
    },
    {
        "type": 1,
        "name": "한국과학기술원대강당",
        "loc": [
            127.36342,
            36.37248
        ]
    },
    {
        "type": 1,
        "name": "한국과학기술원교수회관",
        "loc": [
            127.36456,
            36.3742
        ]
    },
    {
        "type": 2,
        "name": "한국과학기술원교수회관",
        "loc": [
            127.36454,
            36.37418
        ]
    },
    {
        "type": 2,
        "name": "한국과학기술원대강당",
        "loc": [
            127.36341,
            36.3725
        ]
    },
    {
        "type": 2,
        "name": "한국과학기술원본관",
        "loc": [
            127.36069,
            36.36991
        ]
    },
    {
        "type": 2,
        "name": "한국과학기술원오리연못",
        "loc": [
            127.3625,
            36.36737
        ]
    },
    {
        "type": 2,
        "name": "KAIST문지캠퍼스본원뒷편",
        "loc": [
            127.39973,
            36.39383
        ]
    }
]